tongueswitcher/__init__.py
tongueswitcher/executor.py
tongueswitcher/tweet_level.py
tongueswitcher/word_level.py
tongueswitcher/data/clh_pos_editted.json
tongueswitcher/data/combined_bigrams.json
tongueswitcher/data/dictionaries.pkl
tongueswitcher/data/morphmodel_en.pgz
tongueswitcher/data/morphmodel_ger.pgz
tongueswitcher/data/morphmodel_geren.pgz
tongueswitcher-1.0.7.dist-info/METADATA
tongueswitcher-1.0.7.dist-info/WHEEL
tongueswitcher-1.0.7.dist-info/top_level.txt
tongueswitcher-1.0.7.dist-info/RECORD
