Metadata-Version: 2.1
Name: tongueswitcher
Version: 1.0.7
Summary: A package for identification of German--English code-switching
Author: Igor Sterner
Author-email: is473@cam.ac.uk
Classifier: Programming Language :: Python :: 3.7
Classifier: Natural Language :: English
Classifier: Natural Language :: German
Requires-Dist: HanTa (==1.0.0)
Requires-Dist: torch (==1.12.1)
Requires-Dist: transformers (==4.26.0)
Requires-Dist: emoji (==1.7.0)
Requires-Dist: flair (==0.12.2)
Requires-Dist: easydict (==1.10)
